README.md
setup.py
webhook_loghandlers/__init__.py
webhook_loghandlers/handlers.py
webhook_loghandlers.egg-info/PKG-INFO
webhook_loghandlers.egg-info/SOURCES.txt
webhook_loghandlers.egg-info/dependency_links.txt
webhook_loghandlers.egg-info/requires.txt
webhook_loghandlers.egg-info/top_level.txt