Metadata-Version: 1.1
Name: webhook-loghandlers
Version: 0.0.10
Summary: Handlers for the logging module to send logs to discord/slack webhooks
Home-page: https://github.com/MEhrn00/webhook-loghandlers
Author: Matt Ehrnschwender
Author-email: matthewe2020@gmail.com
License: UNKNOWN
Platform: UNKNOWN
Classifier: Programming Language :: Python :: 3
